CHANGES.md
LICENSE.AGPL.md
LICENSE.md
MANIFEST.in
README.md
VERSION
setup.cfg
setup.py
bin/.rc.stack.swp
bin/rc.stack
src/rc.utils.egg-info/PKG-INFO
src/rc.utils.egg-info/SOURCES.txt
src/rc.utils.egg-info/dependency_links.txt
src/rc.utils.egg-info/namespace_packages.txt
src/rc.utils.egg-info/not-zip-safe
src/rc.utils.egg-info/requires.txt
src/rc.utils.egg-info/top_level.txt
src/rc/utils/SDIST
src/rc/utils/VERSION
src/rc/utils/__init__.py
src/rc/utils/misc.py
src/rc/utils/named_pipe.py
src/rc/utils/stream.py
src/rc/utils/tcp_socket.py
src/rc/utils/uds_socket.py
tests/unit_tests/test_named_pipes.py
tests/unit_tests/test_uds.py
tests/unit_tests/__pycache__/test_named_pipes.cpython-38-pytest-6.2.1.pyc
tests/unit_tests/__pycache__/test_uds.cpython-38-pytest-6.2.1.pyc